ruaccent/__init__.py
ruaccent/accent_model.py
ruaccent/char_tokenizer.py
ruaccent/omograph_model.py
ruaccent/ruaccent.py
ruaccent/rule_accent_engine.py
ruaccent/stress_usage_model.py
ruaccent/text_postprocessor.py
ruaccent/text_preprocessor.py
ruaccent/text_split.py
ruaccent/yo_homograph_model.py
ruaccent-1.5.8.3.dist-info/LICENSE
ruaccent-1.5.8.3.dist-info/WHEEL
ruaccent-1.5.8.3.dist-info/METADATA
ruaccent-1.5.8.3.dist-info/RECORD
