Metadata-Version: 2.1
Name: ruaccent
Version: 1.5.8.3
Summary: Russian accentizer
Author-email: Denis Petrov <arduino4b@gmail.com>
Classifier: License :: OSI Approved :: Apache Software License
Requires-Dist: huggingface_hub
Requires-Dist: onnxruntime
Requires-Dist: transformers
Requires-Dist: sentencepiece
Requires-Dist: numpy
Requires-Dist: python-crfsuite
Requires-Dist: razdel
Project-URL: Home, https://github.com/Den4ikAI/ruaccent
